{
  "type": "IntentMaxHistoryTrackerFeaturizer",
  "state_featurizer": {
    "action_texts": [],
    "entity_tag_specs": [],
    "feature_states": {
      "intent": {
        "affirm": 0,
        "back": 1,
        "deny": 2,
        "goodbye": 3,
        "greet": 4,
        "nlu_fallback": 5,
        "out_of_scope": 6,
        "request_bracket_order": 7,
        "request_cancel_all_orders": 8,
        "request_close_position": 9,
        "request_get_open_orders": 10,
        "request_get_orders": 11,
        "request_get_position_by_symbol": 12,
        "request_get_positions": 13,
        "request_limit_order": 14,
        "request_market_order": 15,
        "request_oco_order": 16,
        "request_oto_order": 17,
        "request_stop_limit_order": 18,
        "request_stop_order": 19,
        "request_trailing_stop_order": 20,
        "restart": 21,
        "session_start": 22
      },
      "action_name": {
        "action_listen": 0,
        "action_restart": 1,
        "action_session_start": 2,
        "action_default_fallback": 3,
        "action_deactivate_loop": 4,
        "action_revert_fallback_events": 5,
        "action_default_ask_affirmation": 6,
        "action_default_ask_rephrase": 7,
        "action_two_stage_fallback": 8,
        "action_unlikely_intent": 9,
        "action_back": 10,
        "...": 11,
        "action_extract_slots": 12,
        "action_confirm_and_place_order": 13,
        "action_get_orders": 14,
        "action_cancel_all_orders": 15,
        "action_get_positions": 16,
        "action_get_position_by_symbol": 17,
        "action_close_position": 18,
        "action_get_open_orders": 19,
        "action_summarize_order": 20,
        "action_execute_market_order": 21,
        "action_confirm_bracket_order": 22,
        "action_summarize_trailing_stop": 23,
        "action_place_trailing_stop": 24,
        "action_summarize_limit_order": 25,
        "action_place_limit_order": 26,
        "utter_cancel_all_orders": 27,
        "utter_close_position": 28,
        "utter_confirm_bracket_order": 29,
        "utter_confirm_limit_order": 30,
        "utter_confirm_market_order": 31,
        "utter_confirm_stop_limit_order": 32,
        "utter_confirm_stop_order": 33,
        "utter_confirm_trailing_stop_order": 34,
        "utter_get_open_orders": 35,
        "utter_get_orders": 36,
        "utter_get_position_by_symbol": 37,
        "utter_get_positions": 38,
        "utter_goodbye": 39,
        "utter_greet": 40,
        "utter_iamabot": 41,
        "utter_insufficient_funds": 42,
        "utter_invalid_order_type": 43,
        "utter_invalid_request": 44,
        "utter_invalid_symbol": 45,
        "utter_market_conditions_warning": 46,
        "utter_no_problem": 47,
        "utter_order_canceled": 48,
        "utter_risk_disclaimer": 49,
        "market_order_form": 50,
        "limit_order_form": 51,
        "stop_order_form": 52,
        "stop_limit_order_form": 53,
        "trailing_stop_order_form": 54,
        "bracket_order_form": 55,
        "oto_order_form": 56,
        "oco_order_form": 57
      },
      "entities": {
        "limit_price": 0,
        "notional": 1,
        "qty": 2,
        "side": 3,
        "stop_loss_price": 4,
        "stop_price": 5,
        "symbol": 6,
        "take_profit_price": 7,
        "time_in_force": 8,
        "trail_percent": 9,
        "trail_price": 10
      },
      "slots": {},
      "active_loop": {
        "market_order_form": 0,
        "limit_order_form": 1,
        "stop_order_form": 2,
        "stop_limit_order_form": 3,
        "trailing_stop_order_form": 4,
        "bracket_order_form": 5,
        "oto_order_form": 6,
        "oco_order_form": 7
      }
    }
  },
  "remove_duplicates": true,
  "max_history": 5
}